food_list.py
gui.py
main.py
material_list.py
utils.py
material_food_manager-0.1.0.dist-info/LICENSE
material_food_manager-0.1.0.dist-info/METADATA
material_food_manager-0.1.0.dist-info/WHEEL
material_food_manager-0.1.0.dist-info/top_level.txt
material_food_manager-0.1.0.dist-info/RECORD
