Metadata-Version: 2.2
Name: material-food-manager
Version: 0.1.0
Summary: A simple material food manager application
Author-email: Ömer Tekin <recregt@outlook.com>
License-File: LICENSE
Requires-Dist: gitpython
Requires-Dist: tkinter
